Metadata-Version: 2.1
Name: Surya_Course_maker
Version: 1
Summary: ___                       _    _  _                       
Author: Suraj sharma
Author-email: Surajsharma963472@gmail.com
Keywords: Surya,Game changer,GUI,python tutorial,Suraj,Dictionary,Library,LLAMA,AI
Requires-Dist: PyQt5
Requires-Dist: qtwidgets
Requires-Dist: PyMuPDF
Requires-Dist: webscout
Requires-Dist: fpdf
Requires-Dist: rich
